.travis.yml
AUTHORS
CHANGES
LICENSE
MANIFEST.in
README
requirements.txt
setup.py
lantz/core/__init__.py
lantz/core/__main__.py
lantz/core/action.py
lantz/core/config.py
lantz/core/dochelper.py
lantz/core/driver.py
lantz/core/errors.py
lantz/core/feat.py
lantz/core/flock.py
lantz/core/foreign.py
lantz/core/helpers.py
lantz/core/log.py
lantz/core/messagebased.py
lantz/core/mfeats.py
lantz/core/processors.py
lantz/core/testsuite/__init__.py
lantz/core/testsuite/build
lantz/core/testsuite/simplelib.c
lantz/core/testsuite/simplelib.h
lantz/core/testsuite/test_action.py
lantz/core/testsuite/test_dictfeat.py
lantz/core/testsuite/test_driver.py
lantz/core/testsuite/test_feat.py
lantz/core/testsuite/test_mfeat.py
lantz/core/testsuite/test_processors.py
lantz_core.egg-info/PKG-INFO
lantz_core.egg-info/SOURCES.txt
lantz_core.egg-info/dependency_links.txt
lantz_core.egg-info/entry_points.txt
lantz_core.egg-info/not-zip-safe
lantz_core.egg-info/requires.txt
lantz_core.egg-info/top_level.txt